integration_tools/Constants.py
integration_tools/IntegrativeGAN.py
integration_tools/__init__.py
integration_tools/_types.py
integration_tools/data_integration.py
integration_tools/mulvae.py
integration_tools/stdvae.py
integration_tools/ProjectionModels/Base.py
integration_tools/ProjectionModels/__init__.py
integration_tools/ProjectionModels/stdvae.py
integration_tools/discrimantors_collection/__init__.py
integration_tools/discrimantors_collection/base.py
integration_tools/generators_collection/__init__.py
integration_tools/generators_collection/base.py
integration_tools/utils/__init__.py
integration_tools/utils/data/__init__.py
integration_tools/utils/data/data_classes.py
integration_tools/utils/models/__init__.py
integration_tools/utils/models/learning_utils.py
integration_tools/utils/parser/__init__.py
integration_tools/utils/parser/parser.py
integration_tools/utils/transforms/__init__.py
integration_tools/utils/transforms/transforms_classes.py
integration_tools-0.7.1.dist-info/LICENSE
integration_tools-0.7.1.dist-info/METADATA
integration_tools-0.7.1.dist-info/WHEEL
integration_tools-0.7.1.dist-info/top_level.txt
integration_tools-0.7.1.dist-info/RECORD
