Metadata-Version: 2.1
Name: integration-tools
Version: 0.7.1
Summary: A package in development stages which allows to integrate few data-sets using machine learning tools
Home-page: https://github.com/sharon200102/integration_tools/tree/update_to_pytorch_lightning
Author: Sharon Komissarov
Author-email: sharon200102@gmail.com
License: MIT License
Platform: UNKNOWN
Requires-Dist: torch
Requires-Dist: pandas
Requires-Dist: typing
Requires-Dist: argparse
Requires-Dist: pytorch-lightning
